pyFC/__init__.py
pyFC/clouds.py
pyFC/mathtools.py
pyFC/parsetools.py
pyFC/test_clouds.py
pyFC/utils.py
pyFC-0.1.7.dist-info/COPYING.txt
pyFC-0.1.7.dist-info/METADATA
pyFC-0.1.7.dist-info/WHEEL
pyFC-0.1.7.dist-info/top_level.txt
pyFC-0.1.7.dist-info/RECORD
