Metadata-Version: 2.1
Name: pyFC
Version: 0.1.7
Summary: Fractal cube generator, analyzer and visualizer
Home-page: http://www.ccs.tsukuba.ac.jp/Astro/Members/ayw/code/pyFC/index.html
Author: Alexander Y. Wagner
Author-email: alexander.y.wagner@gmail.com
License: UNKNOWN
Download-URL: https://bitbucket.org/pandante/pyfc.git
Keywords: clouds,astrophysics,simulation,hydrodynamics,cfd,initial conditions,fractal
Platform: UNKNOWN
Classifier: Programming Language :: Python
Classifier: Programming Language :: Python :: 3
Classifier: Development Status :: 4 - Beta
Classifier: Intended Audience :: Science/Research
Classifier: Intended Audience :: Developers
Classifier: License :: OSI Approved :: GNU Library or Lesser General Public License (LGPL)
Classifier: Operating System :: OS Independent
Classifier: Topic :: Scientific/Engineering :: Astronomy
Classifier: Topic :: Scientific/Engineering :: Atmospheric Science
Classifier: Topic :: Software Development :: Libraries :: Python Modules
Requires: wheel
Requires: numpy
Requires: scipy
